[{"id":2,"category":"bags","price":"106","importance":"mid","date":"2024-11-10T12:48:50.061Z"},{"id":3,"category":"makeup","price":"1506","importance":"mid","date":"2024-11-10T12:52:24.638Z"},{"id":4,"category":"cat","price":"50","importance":"mid","date":"2024-11-14T12:10:02.874Z"},{"id":5,"category":"Food","price":20,"importance":"high","date":"2024-11-14T13:33:42.383Z"},{"id":6,"category":"dog treats","price":20,"importance":"high","date":"2024-11-14T13:33:47.354Z"},{"id":7,"category":"dog treats","price":20,"importance":"high","date":"2024-11-14T13:34:18.298Z"}]